<?xml version="1.0" encoding="utf-8" ?>
<dwsync>
<file name="jquery.pagepiling.min.js" server="ftpupload.net//ictsba5m03.epizy.com/htdocs/" local="132268505690000000" remote="132269797200000000" Dst="0" />
<file name="Style.css" server="ftpupload.net//ictsba5m03.epizy.com/htdocs/" local="132268505690000000" remote="132269797200000000" Dst="0" />
<file name="jquery.pagepiling.css" server="ftpupload.net//ictsba5m03.epizy.com/htdocs/" local="132268558364700000" remote="132269797200000000" Dst="0" />
<file name="jquery.pagepiling.js" server="ftpupload.net//ictsba5m03.epizy.com/htdocs/" local="132268505690000000" remote="132269797200000000" Dst="0" />
<file name="gulpfile.js" server="ftpupload.net//ictsba5m03.epizy.com/htdocs/" local="132268505710000000" remote="132269797200000000" Dst="0" />
<file name="popup.html" server="ftpupload.net//ictsba5m03.epizy.com/htdocs/" local="132270257940000000" remote="132269797200000000" Dst="0" />
<file name="jquery.pagepiling.css" server="files.000webhost.com//public_html/" local="132268558364700000" remote="132268856400000000" Dst="0" />
<file name="Style.css" server="files.000webhost.com//public_html/" local="132268505690000000" remote="132268856400000000" Dst="0" />
<file name="jquery.pagepiling.min.js" server="files.000webhost.com//public_html/" local="132268505690000000" remote="132268857000000000" Dst="0" />
<file name="popup.html" server="files.000webhost.com//public_html/" local="132270257940000000" remote="132269969400000000" Dst="0" />
<file name="gulpfile.js" server="files.000webhost.com//public_html/" local="132268505710000000" remote="132269974800000000" Dst="0" />
<file name="jquery.pagepiling.js" server="files.000webhost.com//public_html/" local="132268505690000000" remote="132269974800000000" Dst="0" />
<file name="report.txt" server="files.000webhost.com//public_html/" local="132268217400000000" remote="132268217400000000" Dst="0" />
</dwsync>